docs/Makefile
docs/conf.py
docs/index.rst
kw/structlog_config/__init__.py
kw/structlog_config/config.py
kw/structlog_config/processors.py
test/__init__.py
test/integration/__init__.py
test/unit/__init__.py
test/unit/test_processors.py
kiwi_structlog_config-0.3.6.dist-info/METADATA
kiwi_structlog_config-0.3.6.dist-info/WHEEL
kiwi_structlog_config-0.3.6.dist-info/top_level.txt
kiwi_structlog_config-0.3.6.dist-info/RECORD
