Metadata-Version: 2.4
Name: kiwi-structlog-config
Version: 0.3.6
Home-page: https://github.com/kiwicom/kiwi-structlog-config
Author: Booking Backend team
Author-email: bookingbe@kiwi.com
Classifier: Development Status :: 4 - Beta
Classifier: Environment :: Console
Classifier: Operating System :: OS Independent
Classifier: Programming Language :: Python :: 3
Requires-Dist: colorama
Requires-Dist: simplejson
Requires-Dist: structlog
Dynamic: author
Dynamic: author-email
Dynamic: classifier
Dynamic: home-page
Dynamic: requires-dist
